{
  "chapter_name": "Η ΑΤΤΙΚΗ",
  "word_list_page_number": 247,
  "exercise_page_range": [
    243,
    246
  ],
  "sections": [
    {
      "section": "Ῥήματα",
      "words": [
        {
          "book_entry": "ἀπέχω",
          "first_occurrence": [
            62,
            6
          ]
        },
        {
          "book_entry": "ἐκπλέω",
          "first_occurrence": [
            64,
            7
          ]
        },
        {
          "book_entry": "νικάω"
        },
        {
          "book_entry": "οἰκοδομέω",
          "first_occurrence": [
            80,
            2
          ]
        },
        {
          "book_entry": "ὁρμίζω",
          "first_occurrence": [
            55,
            2
          ]
        },
        {
          "book_entry": "ῥέω"
        },
        {
          "book_entry": "φύω",
          "first_occurrence": [
            20,
            2
          ]
        }
      ]
    },
    {
      "section": "Κύρια ὀνόματα",
      "words": [
        {
          "book_entry": "Ἀκτή, ἡ"
        },
        {
          "book_entry": "Ἠριδανός, ὁ"
        },
        {
          "book_entry": "Ἰλισός, ὁ"
        },
        {
          "book_entry": "Μαραθών, ὁ"
        },
        {
          "book_entry": "Παρθενών, ὁ"
        },
        {
          "book_entry": "Πάρις, ὁ"
        },
        {
          "book_entry": "Πειραιεύς, ὁ"
        },
        {
          "book_entry": "Πτολεμαίος, ὁ"
        },
        {
          "book_entry": "Σούνιον, τό"
        },
        {
          "book_entry": "Φάληρον, τό"
        }
      ]
    },
    {
      "section": "Ὀνόματα",
      "words": [
        {
          "book_entry": "αἰγιαλός, ὁ",
          "first_occurrence": [
            53,
            3
          ]
        },
        {
          "book_entry": "ἄκρον, τό",
          "first_occurrence": [
            25,
            5
          ]
        },
        {
          "book_entry": "ἀκτή, ἡ",
          "first_occurrence": [
            50,
            3
          ]
        },
        {
          "book_entry": "ἀμυγδαλῆ, ἡ",
          "first_occurrence": [
            10,
            4
          ]
        },
        {
          "book_entry": "_βαθμός, ὁ_"
        },
        {
          "book_entry": "κλῖμα, τό",
          "first_occurrence": [
            4,
            1
          ]
        },
        {
          "book_entry": "λιθοτομία, ἡ",
          "first_occurrence": [
            20,
            7
          ]
        },
        {
          "book_entry": "λιθοτόμος, ὁ"
        },
        {
          "book_entry": "λιμήν, ὁ",
          "first_occurrence": [
            58,
            1
          ]
        },
        {
          "book_entry": "λόφος, ὁ",
          "first_occurrence": [
            47,
            1
          ]
        },
        {
          "book_entry": "ναύαρχος, ὁ",
          "first_occurrence": [
            78,
            6
          ]
        },
        {
          "book_entry": "ναυμαχία, ἡ",
          "first_occurrence": [
            70,
            1
          ]
        },
        {
          "book_entry": "ὅρμος, ὁ",
          "first_occurrence": [
            56,
            2
          ]
        },
        {
          "book_entry": "παρθένος, ἡ"
        },
        {
          "book_entry": "πεδίον, τό",
          "first_occurrence": [
            27,
            5
          ]
        },
        {
          "book_entry": "πλευρά, ἡ",
          "first_occurrence": [
            49,
            1
          ]
        },
        {
          "book_entry": "στόλος, ὁ",
          "first_occurrence": [
            71,
            5
          ]
        },
        {
          "book_entry": "στρατός, ὁ",
          "first_occurrence": [
            30,
            2
          ]
        },
        {
          "book_entry": "συκῆ, ἡ",
          "first_occurrence": [
            10,
            1
          ]
        },
        {
          "book_entry": "τεῖχος, τό",
          "first_occurrence": [
            79,
            5
          ]
        },
        {
          "book_entry": "Κηφισός, ὁ"
        }
      ]
    },
    {
      "section": "Ἐπίθετα",
      "words": [
        {
          "book_entry": "Αἰγύπτιος, -α, -ον",
          "first_occurrence": [
            79,
            2
          ]
        },
        {
          "book_entry": "ἀμφιθάλασσος, -ον",
          "first_occurrence": [
            48,
            3
          ]
        },
        {
          "book_entry": "ἀττικός, -ή, -όν"
        },
        {
          "book_entry": "ἐμπορικός, -ή, -όν",
          "first_occurrence": [
            66,
            6
          ]
        },
        {
          "book_entry": "ἔρημος, -ον",
          "first_occurrence": [
            77,
            7
          ]
        },
        {
          "book_entry": "ἐχθρός, -ά, -όν",
          "first_occurrence": [
            29,
            7
          ]
        },
        {
          "book_entry": "_θετικός, -ή, -όν_"
        },
        {
          "book_entry": "καρποφόρος, -ον",
          "first_occurrence": [
            3,
            1
          ]
        },
        {
          "book_entry": "Μηδικός, -ή, -όν",
          "first_occurrence": [
            29,
            4
          ]
        },
        {
          "book_entry": "ὀρεινός, -ή, -όν",
          "first_occurrence": [
            15,
            7
          ]
        },
        {
          "book_entry": "παλαιός, -ά, -όν",
          "first_occurrence": [
            52,
            1
          ]
        },
        {
          "book_entry": "Περσικός, -ή, -όν",
          "first_occurrence": [
            30,
            1
          ]
        },
        {
          "book_entry": "_συγκριτικός, -ή, -όν_"
        },
        {
          "book_entry": "_ὑπερθετικός, -ή, -όν_"
        }
      ]
    },
    {
      "section": "Ἐπιρρήματα",
      "words": [
        {
          "book_entry": "ὅπου",
          "first_occurrence": [
            28,
            7
          ]
        }
      ]
    }
  ]
}